gs_ai_package/__init__.py
gs_ai_package/direction_processor.py
gs_ai_package-0.1.4.dist-info/METADATA
gs_ai_package-0.1.4.dist-info/WHEEL
gs_ai_package-0.1.4.dist-info/top_level.txt
gs_ai_package-0.1.4.dist-info/RECORD
