Metadata-Version: 2.1
Name: gs-ai-package
Version: 0.1.4
Summary: Package per associare a dati trasporto pubblico la direzione della tratta
Home-page: https://gitlab.greenshare.it/pietro.cosseddu/gs-ai-package.git
Author: PietroCosseddu
Author-email: pietro.cosseddu@green-share.it
Classifier: Programming Language :: Python :: 3
Classifier: Operating System :: OS Independent
Requires-Python: >=3.7
Requires-Dist: pandas>=1.0.0
Requires-Dist: numpy>=1.18.0
